aqua_cli/__init__.py
aqua_cli/__main__.py
aqua_cli/cli/__init__.py
aqua_cli/cli/check_intake.py
aqua_cli/cli/arguments/__init__.py
aqua_cli/cli/arguments/about.py
aqua_cli/cli/arguments/change_amount.py
aqua_cli/cli/arguments/get.py
aqua_cli/cli/arguments/setup.py
aqua_cli/database/__init__.py
aqua_cli/database/create_connection.py
aqua_cli/database/execute_query.py
aqua_cli/utils/__init__.py
aqua_cli/utils/check_update.py
aqua_cli/utils/files_location.py
aqua_cli-1.1.2.dist-info/LICENSE
aqua_cli-1.1.2.dist-info/METADATA
aqua_cli-1.1.2.dist-info/WHEEL
aqua_cli-1.1.2.dist-info/entry_points.txt
aqua_cli-1.1.2.dist-info/top_level.txt
aqua_cli-1.1.2.dist-info/RECORD
