Metadata-Version: 2.1
Name: aqua-cli
Version: 1.1.2
Summary: A simple water tracking CLI. Track your water intake.
Home-page: https://github.com/nyf9b/aqua-cli
Author: nyf9b
License: GNU General Public License v3
Keywords: water
Classifier: License :: OSI Approved :: GNU General Public License v3 (GPLv3)
Classifier: Programming Language :: Python :: 3
Classifier: Programming Language :: Python :: 3 :: Only
Classifier: Operating System :: OS Independent
License-File: LICENSE
Requires-Dist: requests
Requires-Dist: platformdirs
